LICENSE
MANIFEST.in
README.rst
setup.py
nansat/__init__.py
nansat/domain.py
nansat/exceptions.py
nansat/exporter.py
nansat/figure.py
nansat/geolocation.py
nansat/nansat.py
nansat/node.py
nansat/nsr.py
nansat/pointbrowser.py
nansat/tools.py
nansat/utils.py
nansat/vrt.py
nansat/warnings.py
nansat.egg-info/PKG-INFO
nansat.egg-info/SOURCES.txt
nansat.egg-info/dependency_links.txt
nansat.egg-info/requires.txt
nansat.egg-info/top_level.txt
nansat/fonts/DejaVuSans.ttf
nansat/mappers/__init__.py
nansat/mappers/envisat.py
nansat/mappers/get_grib.pl
nansat/mappers/get_inv.pl
nansat/mappers/globcolour.py
nansat/mappers/hdf4_mapper.py
nansat/mappers/mapper_aapp_l1b.py
nansat/mappers/mapper_aapp_l1c.py
nansat/mappers/mapper_amsr2_l1r.py
nansat/mappers/mapper_amsr2_l3.py
nansat/mappers/mapper_amsre_uham_leadfraction.py
nansat/mappers/mapper_arome.py
nansat/mappers/mapper_asar.py
nansat/mappers/mapper_ascat.py
nansat/mappers/mapper_aster_l1a.py
nansat/mappers/mapper_aster_l1b.py
nansat/mappers/mapper_case2reg.py
nansat/mappers/mapper_cmems.py
nansat/mappers/mapper_csks.py
nansat/mappers/mapper_ecmwf_metno.py
nansat/mappers/mapper_emodnet.py
nansat/mappers/mapper_generic.py
nansat/mappers/mapper_geostationary.py
nansat/mappers/mapper_globcolour_l3b.py
nansat/mappers/mapper_globcolour_l3m.py
nansat/mappers/mapper_goci_l1.py
nansat/mappers/mapper_hirlam.py
nansat/mappers/mapper_hirlam_wind_netcdf.py
nansat/mappers/mapper_kmss.py
nansat/mappers/mapper_landsat.py
nansat/mappers/mapper_meris_l1.py
nansat/mappers/mapper_meris_l2.py
nansat/mappers/mapper_metno_hfr.py
nansat/mappers/mapper_metno_hires_seaice.py
nansat/mappers/mapper_metno_local_hires_seaice.py
nansat/mappers/mapper_mod44w.py
nansat/mappers/mapper_modis_l1.py
nansat/mappers/mapper_ncep.py
nansat/mappers/mapper_ncep_wind.py
nansat/mappers/mapper_ncep_wind_online.py
nansat/mappers/mapper_netcdf_cf.py
nansat/mappers/mapper_netcdf_cf_sentinel1.py
nansat/mappers/mapper_nora10_local_vpv.py
nansat/mappers/mapper_obpg_l2.py
nansat/mappers/mapper_obpg_l2_nc.py
nansat/mappers/mapper_obpg_l3.py
nansat/mappers/mapper_ocean_productivity.py
nansat/mappers/mapper_opendap_arome.py
