Metadata-Version: 1.2
Name: nansat
Version: 1.5.1
Summary: A scientist friendly Python toolbox for processing 2D satellite Earth observation data
Home-page: https://github.com/nansencenter/nansat
Author: Anton Korosov, Morten W. Hansen, Kunt-Frode Dagestad, Aleksander Vines, Asuka Yamakawa, Artem Moiseev, Mohamed Babiker
Author-email: nansat-dev@googlegroups.com
Maintainer: Nansat Developers
Maintainer-email: nansat-dev@googlegroups.com
License: GNU General Public License
Download-URL: https://github.com/nansencenter/nansat
Platform: Linux
Platform: OS X
Platform: Windows
Classifier: Development Status :: 5 - Production/Stable
Classifier: Environment :: Console
Classifier: Intended Audience :: Information Technology
Classifier: Intended Audience :: Science/Research
Classifier: License :: OSI Approved :: GNU General Public License v3 (GPLv3)
Classifier: Natural Language :: English
Classifier: Operating System :: OS Independent
Classifier: Programming Language :: Python :: 2.7
Classifier: Programming Language :: Python :: 3.5
Classifier: Programming Language :: Python :: 3.6
Classifier: Topic :: Scientific/Engineering
Classifier: Topic :: Scientific/Engineering :: Atmospheric Science
Classifier: Topic :: Scientific/Engineering :: Information Analysis
Classifier: Topic :: Utilities
